README.md
README.rst
setup.cfg
setup.py
etnotify/__init__.py
etnotify/__main__.py
etnotify/etnotify.py
etnotify.egg-info/PKG-INFO
etnotify.egg-info/SOURCES.txt
etnotify.egg-info/dependency_links.txt
etnotify.egg-info/entry_points.txt
etnotify.egg-info/requires.txt
etnotify.egg-info/top_level.txt