Metadata-Version: 1.1
Name: etnotify
Version: 1.3
Summary: Notifier script for ETNA.
Home-page: https://github.com/tbobm/etnotify
Author: Theo "Bob" Massard
Author-email: massar_t@etna-alternance.net
License: MIT
Platform: UNKNOWN
Classifier: License :: OSI Approved :: MIT License
Classifier: Programming Language :: Python
Classifier: Programming Language :: Python :: 3
Classifier: Programming Language :: Python :: Implementation :: CPython
Classifier: Programming Language :: Python :: Implementation :: PyPy
